{
  "db_name": "PostgreSQL",
  "query": "SELECT sv.id, sv.secret_id, sv.version, sv.encrypted_value, sv.created_at, sv.created_by\n         FROM secret_versions sv\n         JOIN secrets s ON sv.secret_id = s.id\n         WHERE s.org_id = $1 AND s.name = $2 AND s.deleted_at IS NULL AND sv.version = s.current_version",
  "describe": {
    "columns": [
      {
        "ordinal": 0,
        "name": "id",
        "type_info": "Uuid"
      },
      {
        "ordinal": 1,
        "name": "secret_id",
        "type_info": "Uuid"
      },
      {
        "ordinal": 2,
        "name": "version",
        "type_info": "Int4"
      },
      {
        "ordinal": 3,
        "name": "encrypted_value",
        "type_info": "Bytea"
      },
      {
        "ordinal": 4,
        "name": "created_at",
        "type_info": "Timestamptz"
      },
      {
        "ordinal": 5,
        "name": "created_by",
        "type_info": "Uuid"
      }
    ],
    "parameters": {
      "Left": [
        "Uuid",
        "Text"
      ]
    },
    "nullable": [
      false,
      false,
      false,
      false,
      false,
      true
    ]
  },
  "hash": "21f71351f0f5cf6692771f1a0cc96e7eec6e9786ede4e069609e74e611252741"
}
