{
  "db_name": "PostgreSQL",
  "query": "INSERT INTO executions (approval_id, org_id, status, remember, remember_keys, remember_rule_ttl, expires_at)\n         VALUES ($1, $2, 'pending', $3, $4, $5, $6)\n         RETURNING id, approval_id, org_id, status, remember, remember_keys, remember_rule_ttl, result, error, triggered_by, started_at, completed_at, expires_at, created_at, result_viewed_at",
  "describe": {
    "columns": [
      {
        "ordinal": 0,
        "name": "id",
        "type_info": "Uuid"
      },
      {
        "ordinal": 1,
        "name": "approval_id",
        "type_info": "Uuid"
      },
      {
        "ordinal": 2,
        "name": "org_id",
        "type_info": "Uuid"
      },
      {
        "ordinal": 3,
        "name": "status",
        "type_info": "Text"
      },
      {
        "ordinal": 4,
        "name": "remember",
        "type_info": "Bool"
      },
      {
        "ordinal": 5,
        "name": "remember_keys",
        "type_info": "TextArray"
      },
      {
        "ordinal": 6,
        "name": "remember_rule_ttl",
        "type_info": "Timestamptz"
      },
      {
        "ordinal": 7,
        "name": "result",
        "type_info": "Jsonb"
      },
      {
        "ordinal": 8,
        "name": "error",
        "type_info": "Text"
      },
      {
        "ordinal": 9,
        "name": "triggered_by",
        "type_info": "Text"
      },
      {
        "ordinal": 10,
        "name": "started_at",
        "type_info": "Timestamptz"
      },
      {
        "ordinal": 11,
        "name": "completed_at",
        "type_info": "Timestamptz"
      },
      {
        "ordinal": 12,
        "name": "expires_at",
        "type_info": "Timestamptz"
      },
      {
        "ordinal": 13,
        "name": "created_at",
        "type_info": "Timestamptz"
      },
      {
        "ordinal": 14,
        "name": "result_viewed_at",
        "type_info": "Timestamptz"
      }
    ],
    "parameters": {
      "Left": [
        "Uuid",
        "Uuid",
        "Bool",
        "TextArray",
        "Timestamptz",
        "Timestamptz"
      ]
    },
    "nullable": [
      false,
      false,
      false,
      false,
      false,
      true,
      true,
      true,
      true,
      true,
      true,
      true,
      false,
      false,
      true
    ]
  },
  "hash": "7e2e4397beb44db8b5f54a2d5c82034d20e205d69de348c71e40bbc70143b59f"
}
